Metadata-Version: 2.4
Name: taha-apimatic-qa-sdk
Version: 1.5.8
Summary: test
Author-email: qa test <taha.ali@apimatic.io>
Project-URL: Documentation, https://app.dev.apimatic.io/dashboard
Keywords: test
Requires-Python: >=3.7
License-File: LICENSE
Requires-Dist: apimatic-core>=0.2.17,~=0.2.0
Requires-Dist: apimatic-core-interfaces>=0.1.5,~=0.1.0
Requires-Dist: apimatic-requests-client-adapter>=0.1.6,~=0.1.0
Provides-Extra: testutils
Requires-Dist: pytest>=7.2.2; extra == "testutils"
Dynamic: license-file
